MANIFEST.in
README.txt
setup.py
c2/__init__.py
c2.app.streamingaws.egg-info/PKG-INFO
c2.app.streamingaws.egg-info/SOURCES.txt
c2.app.streamingaws.egg-info/dependency_links.txt
c2.app.streamingaws.egg-info/entry_points.txt
c2.app.streamingaws.egg-info/namespace_packages.txt
c2.app.streamingaws.egg-info/not-zip-safe
c2.app.streamingaws.egg-info/requires.txt
c2.app.streamingaws.egg-info/top_level.txt
c2/app/__init__.py
c2/app/streamingaws/__init__.py
c2/app/streamingaws/aws_utils.py
c2/app/streamingaws/configure.zcml
c2/app/streamingaws/indexer.py
c2/app/streamingaws/streamingvideo.py
c2/app/streamingaws/tests.py
c2/app/streamingaws/version.txt
c2/app/streamingaws/controlpanel/__init__.py
c2/app/streamingaws/controlpanel/configure.zcml
c2/app/streamingaws/controlpanel/interfaces.py
c2/app/streamingaws/controlpanel/main.py
c2/app/streamingaws/controlpanel/manage_aws_settings.py
c2/app/streamingaws/controlpanel/manage_s3_video.pt
c2/app/streamingaws/controlpanel/manage_s3_video.py
c2/app/streamingaws/profiles/default/catalog.xml
c2/app/streamingaws/profiles/default/controlpanel.xml
c2/app/streamingaws/profiles/default/metadata.xml
c2/app/streamingaws/profiles/default/registry.xml
c2/app/streamingaws/profiles/default/types.xml
c2/app/streamingaws/profiles/default/types/streamingvideo.xml
c2/app/streamingaws/static/videojs/video-js.min.css
c2/app/streamingaws/static/videojs/video-js.swf
c2/app/streamingaws/static/videojs/video.js
c2/app/streamingaws/static/videojs/font/vjs.eot
c2/app/streamingaws/static/videojs/font/vjs.svg
c2/app/streamingaws/static/videojs/font/vjs.ttf
c2/app/streamingaws/static/videojs/font/vjs.woff
c2/app/streamingaws/streamingvideo_templates/frameview.pt
c2/app/streamingaws/streamingvideo_templates/inlinetags.pt
c2/app/streamingaws/streamingvideo_templates/video_player_macros.pt
c2/app/streamingaws/streamingvideo_templates/view.pt
docs/HISTORY.txt
docs/INSTALL.txt
docs/LICENSE.GPL
docs/LICENSE.txt