Metadata-Version: 1.1
Name: c2.app.streamingaws
Version: 1.0a2
Summary: This product supports streaming content in AWS on Plone. It's using S3, CloudFront and Amazon Elastic Transcoder.
Home-page: http://www.cmscom.jp
Author: Manabu TERADA
Author-email: terada@cmscom.jp
License: GPL
Keywords: plone video streaming aws cloutfront
Platform: UNKNOWN
Classifier: Framework :: Plone
Classifier: Programming Language :: Python
